{
    "swagger": "2.0",
    "info": {
        "description": "API Server for TodoList Application",
        "title": "Todo App API",
        "contact": {},
        "version": "1.0"
    },
    "host": "localhost:8000",
    "basePath": "/",
    "paths": {
        "/api/items/{id}": {
            "get": {
                "security": [
                    {
                        "ApiKeyAuth": []
                    }
                ],
                "description": "Get list item using itemID",
                "consumes": [
                    "application/json"
                ],
                "produces": [
                    "application/json"
                ],
                "tags": [
                    "items"
                ],
                "summary": "Get List Item By Id",
                "parameters": [
                    {
                        "type": "integer",
                        "description": "item ID",
                        "name": "id",
                        "in": "path",
                        "required": true
                    }
                ],
                "responses": {
                    "200": {
                        "description": "OK",
                        "schema": {
                            "$ref": "#/definitions/models.TodoItem"
                        }
                    },
                    "400": {
                        "description": "Bad Request",
                        "schema": {
                            "$ref": "#/definitions/handler.errorResponse"
                        }
                    },
                    "404": {
                        "description": "Not Found",
                        "schema": {
                            "$ref": "#/definitions/handler.errorResponse"
                        }
                    },
                    "500": {
                        "description": "Internal Server Error",
                        "schema": {
                            "$ref": "#/definitions/handler.errorResponse"
                        }
                    },
                    "default": {
                        "description": "",
                        "schema": {
                            "$ref": "#/definitions/handler.errorResponse"
                        }
                    }
                }
            },
            "put": {
                "security": [
                    {
                        "ApiKeyAuth": []
                    }
                ],
                "description": "Update list item using itemID",
                "consumes": [
                    "application/json"
                ],
                "produces": [
                    "application/json"
                ],
                "tags": [
                    "items"
                ],
                "summary": "Update List item By Id",
                "parameters": [
                    {
                        "description": "Update item input",
                        "name": "input",
                        "in": "body",
                        "required": true,
                        "schema": {
                            "$ref": "#/definitions/models.UpdateItemInput"
                        }
                    },
                    {
                        "type": "integer",
                        "description": "item ID",
                        "name": "id",
                        "in": "path",
                        "required": true
                    }
                ],
                "responses": {
                    "200": {
                        "description": "status",
                        "schema": {
                            "type": "string"
                        }
                    },
                    "400": {
                        "description": "Bad Request",
                        "schema": {
                            "$ref": "#/definitions/handler.errorResponse"
                        }
                    },
                    "404": {
                        "description": "Not Found",
                        "schema": {
                            "$ref": "#/definitions/handler.errorResponse"
                        }
                    },
                    "500": {
                        "description": "Internal Server Error",
                        "schema": {
                            "$ref": "#/definitions/handler.errorResponse"
                        }
                    },
                    "default": {
                        "description": "",
                        "schema": {
                            "$ref": "#/definitions/handler.errorResponse"
                        }
                    }
                }
            },
            "delete": {
                "security": [
                    {
                        "ApiKeyAuth": []
                    }
                ],
                "description": "Delete list item using itemID",
                "consumes": [
                    "application/json"
                ],
                "produces": [
                    "application/json"
                ],
                "tags": [
                    "items"
                ],
                "summary": "Delete List Item By Id",
                "parameters": [
                    {
                        "type": "integer",
                        "description": "item ID",
                        "name": "id",
                        "in": "path",
                        "required": true
                    }
                ],
                "responses": {
                    "200": {
                        "description": "status",
                        "schema": {
                            "type": "string"
                        }
                    },
                    "400": {
                        "description": "Bad Request",
                        "schema": {
                            "$ref": "#/definitions/handler.errorResponse"
                        }
                    },
                    "404": {
                        "description": "Not Found",
                        "schema": {
                            "$ref": "#/definitions/handler.errorResponse"
                        }
                    },
                    "500": {
                        "description": "Internal Server Error",
                        "schema": {
                            "$ref": "#/definitions/handler.errorResponse"
                        }
                    },
                    "default": {
                        "description": "",
                        "schema": {
                            "$ref": "#/definitions/handler.errorResponse"
                        }
                    }
                }
            }
        },
        "/api/lists": {
            "get": {
                "security": [
                    {
                        "ApiKeyAuth": []
                    }
                ],
                "description": "Get all user lists",
                "consumes": [
                    "application/json"
                ],
                "produces": [
                    "application/json"
                ],
                "tags": [
                    "lists"
                ],
                "summary": "Get All Lists",
                "responses": {
                    "200": {
                        "description": "OK",
                        "schema": {
                            "$ref": "#/definitions/handler.getAllListsResponse"
                        }
                    },
                    "400": {
                        "description": "Bad Request",
                        "schema": {
                            "$ref": "#/definitions/handler.errorResponse"
                        }
                    },
                    "404": {
                        "description": "Not Found",
                        "schema": {
                            "$ref": "#/definitions/handler.errorResponse"
                        }
                    },
                    "500": {
                        "description": "Internal Server Error",
                        "schema": {
                            "$ref": "#/definitions/handler.errorResponse"
                        }
                    },
                    "default": {
                        "description": "",
                        "schema": {
                            "$ref": "#/definitions/handler.errorResponse"
                        }
                    }
                }
            },
            "post": {
                "security": [
                    {
                        "ApiKeyAuth": []
                    }
                ],
                "description": "Create new todo list",
                "consumes": [
                    "application/json"
                ],
                "produces": [
                    "application/json"
                ],
                "tags": [
                    "lists"
                ],
                "summary": "Create todo list",
                "parameters": [
                    {
                        "description": "list info",
                        "name": "input",
                        "in": "body",
                        "required": true,
                        "schema": {
                            "$ref": "#/definitions/models.CreateListInput"
                        }
                    }
                ],
                "responses": {
                    "201": {
                        "description": "Created",
                        "schema": {
                            "type": "integer"
                        }
                    },
                    "400": {
                        "description": "Bad Request",
                        "schema": {
                            "$ref": "#/definitions/handler.errorResponse"
                        }
                    },
                    "404": {
                        "description": "Not Found",
                        "schema": {
                            "$ref": "#/definitions/handler.errorResponse"
                        }
                    },
                    "500": {
                        "description": "Internal Server Error",
                        "schema": {
                            "$ref": "#/definitions/handler.errorResponse"
                        }
                    },
                    "default": {
                        "description": "",
                        "schema": {
                            "$ref": "#/definitions/handler.errorResponse"
                        }
                    }
                }
            }
        },
        "/api/lists/{id}": {
            "get": {
                "security": [
                    {
                        "ApiKeyAuth": []
                    }
                ],
                "description": "Get list using listID",
                "consumes": [
                    "application/json"
                ],
                "produces": [
                    "application/json"
                ],
                "tags": [
                    "lists"
                ],
                "summary": "Get List By Id",
                "parameters": [
                    {
                        "type": "integer",
                        "description": "list ID",
                        "name": "id",
                        "in": "path",
                        "required": true
                    }
                ],
                "responses": {
                    "200": {
                        "description": "OK",
                        "schema": {
                            "$ref": "#/definitions/models.ListItem"
                        }
                    },
                    "400": {
                        "description": "Bad Request",
                        "schema": {
                            "$ref": "#/definitions/handler.errorResponse"
                        }
                    },
                    "404": {
                        "description": "Not Found",
                        "schema": {
                            "$ref": "#/definitions/handler.errorResponse"
                        }
                    },
                    "500": {
                        "description": "Internal Server Error",
                        "schema": {
                            "$ref": "#/definitions/handler.errorResponse"
                        }
                    },
                    "default": {
                        "description": "",
                        "schema": {
                            "$ref": "#/definitions/handler.errorResponse"
                        }
                    }
                }
            },
            "put": {
                "security": [
                    {
                        "ApiKeyAuth": []
                    }
                ],
                "description": "Update list using listID",
                "consumes": [
                    "application/json"
                ],
                "produces": [
                    "application/json"
                ],
                "tags": [
                    "lists"
                ],
                "summary": "Update List By Id",
                "parameters": [
                    {
                        "description": "Update Input",
                        "name": "input",
                        "in": "body",
                        "required": true,
                        "schema": {
                            "$ref": "#/definitions/models.UpdateListInput"
                        }
                    },
                    {
                        "type": "integer",
                        "description": "list ID",
                        "name": "id",
                        "in": "path",
                        "required": true
                    }
                ],
                "responses": {
                    "200": {
                        "description": "status",
                        "schema": {
                            "type": "string"
                        }
                    },
                    "400": {
                        "description": "Bad Request",
                        "schema": {
                            "$ref": "#/definitions/handler.errorResponse"
                        }
                    },
                    "404": {
                        "description": "Not Found",
                        "schema": {
                            "$ref": "#/definitions/handler.errorResponse"
                        }
                    },
                    "500": {
                        "description": "Internal Server Error",
                        "schema": {
                            "$ref": "#/definitions/handler.errorResponse"
                        }
                    },
                    "default": {
                        "description": "",
                        "schema": {
                            "$ref": "#/definitions/handler.errorResponse"
                        }
                    }
                }
            },
            "delete": {
                "security": [
                    {
                        "ApiKeyAuth": []
                    }
                ],
                "description": "Delete list using listID",
                "consumes": [
                    "application/json"
                ],
                "produces": [
                    "application/json"
                ],
                "tags": [
                    "lists"
                ],
                "summary": "Delete List By Id",
                "parameters": [
                    {
                        "type": "integer",
                        "description": "list ID",
                        "name": "id",
                        "in": "path",
                        "required": true
                    }
                ],
                "responses": {
                    "200": {
                        "description": "status",
                        "schema": {
                            "type": "string"
                        }
                    },
                    "400": {
                        "description": "Bad Request",
                        "schema": {
                            "$ref": "#/definitions/handler.errorResponse"
                        }
                    },
                    "404": {
                        "description": "Not Found",
                        "schema": {
                            "$ref": "#/definitions/handler.errorResponse"
                        }
                    },
                    "500": {
                        "description": "Internal Server Error",
                        "schema": {
                            "$ref": "#/definitions/handler.errorResponse"
                        }
                    },
                    "default": {
                        "description": "",
                        "schema": {
                            "$ref": "#/definitions/handler.errorResponse"
                        }
                    }
                }
            }
        },
        "/api/lists/{id}/items": {
            "get": {
                "security": [
                    {
                        "ApiKeyAuth": []
                    }
                ],
                "description": "Get All todo list items",
                "consumes": [
                    "application/json"
                ],
                "produces": [
                    "application/json"
                ],
                "tags": [
                    "items"
                ],
                "summary": "Get All Lists items",
                "parameters": [
                    {
                        "type": "integer",
                        "description": "list ID",
                        "name": "id",
                        "in": "path",
                        "required": true
                    }
                ],
                "responses": {
                    "200": {
                        "description": "OK",
                        "schema": {
                            "type": "array",
                            "items": {
                                "$ref": "#/definitions/models.TodoItem"
                            }
                        }
                    },
                    "400": {
                        "description": "Bad Request",
                        "schema": {
                            "$ref": "#/definitions/handler.errorResponse"
                        }
                    },
                    "404": {
                        "description": "Not Found",
                        "schema": {
                            "$ref": "#/definitions/handler.errorResponse"
                        }
                    },
                    "500": {
                        "description": "Internal Server Error",
                        "schema": {
                            "$ref": "#/definitions/handler.errorResponse"
                        }
                    },
                    "default": {
                        "description": "",
                        "schema": {
                            "$ref": "#/definitions/handler.errorResponse"
                        }
                    }
                }
            },
            "post": {
                "security": [
                    {
                        "ApiKeyAuth": []
                    }
                ],
                "description": "Create new todo list item",
                "consumes": [
                    "application/json"
                ],
                "produces": [
                    "application/json"
                ],
                "tags": [
                    "items"
                ],
                "summary": "Create todo list item",
                "parameters": [
                    {
                        "type": "integer",
                        "description": "list ID",
                        "name": "id",
                        "in": "path",
                        "required": true
                    },
                    {
                        "description": "item info",
                        "name": "input",
                        "in": "body",
                        "required": true,
                        "schema": {
                            "$ref": "#/definitions/models.CreateTodoItemInp"
                        }
                    }
                ],
                "responses": {
                    "201": {
                        "description": "Created",
                        "schema": {
                            "type": "integer"
                        }
                    },
                    "400": {
                        "description": "Bad Request",
                        "schema": {
                            "$ref": "#/definitions/handler.errorResponse"
                        }
                    },
                    "404": {
                        "description": "Not Found",
                        "schema": {
                            "$ref": "#/definitions/handler.errorResponse"
                        }
                    },
                    "500": {
                        "description": "Internal Server Error",
                        "schema": {
                            "$ref": "#/definitions/handler.errorResponse"
                        }
                    },
                    "default": {
                        "description": "",
                        "schema": {
                            "$ref": "#/definitions/handler.errorResponse"
                        }
                    }
                }
            }
        },
        "/auth/sign-in": {
            "post": {
                "description": "login",
                "consumes": [
                    "application/json"
                ],
                "produces": [
                    "application/json"
                ],
                "tags": [
                    "auth"
                ],
                "summary": "SignIn",
                "parameters": [
                    {
                        "description": "username and passwor",
                        "name": "input",
                        "in": "body",
                        "required": true,
                        "schema": {
                            "$ref": "#/definitions/handler.signInInput"
                        }
                    }
                ],
                "responses": {
                    "200": {
                        "description": "token",
                        "schema": {
                            "type": "string"
                        }
                    },
                    "400": {
                        "description": "Bad Request",
                        "schema": {
                            "$ref": "#/definitions/handler.errorResponse"
                        }
                    },
                    "404": {
                        "description": "Not Found",
                        "schema": {
                            "$ref": "#/definitions/handler.errorResponse"
                        }
                    },
                    "500": {
                        "description": "Internal Server Error",
                        "schema": {
                            "$ref": "#/definitions/handler.errorResponse"
                        }
                    },
                    "default": {
                        "description": "",
                        "schema": {
                            "$ref": "#/definitions/handler.errorResponse"
                        }
                    }
                }
            }
        },
        "/auth/sign-up": {
            "post": {
                "description": "Create new account",
                "consumes": [
                    "application/json"
                ],
                "produces": [
                    "application/json"
                ],
                "tags": [
                    "auth"
                ],
                "summary": "SignUp",
                "parameters": [
                    {
                        "description": "Account info",
                        "name": "input",
                        "in": "body",
                        "required": true,
                        "schema": {
                            "$ref": "#/definitions/models.User"
                        }
                    }
                ],
                "responses": {
                    "200": {
                        "description": "OK",
                        "schema": {
                            "type": "integer"
                        }
                    },
                    "400": {
                        "description": "Bad Request",
                        "schema": {
                            "$ref": "#/definitions/handler.errorResponse"
                        }
                    },
                    "404": {
                        "description": "Not Found",
                        "schema": {
                            "$ref": "#/definitions/handler.errorResponse"
                        }
                    },
                    "500": {
                        "description": "Internal Server Error",
                        "schema": {
                            "$ref": "#/definitions/handler.errorResponse"
                        }
                    },
                    "default": {
                        "description": "",
                        "schema": {
                            "$ref": "#/definitions/handler.errorResponse"
                        }
                    }
                }
            }
        }
    },
    "definitions": {
        "handler.errorResponse": {
            "type": "object",
            "properties": {
                "message": {
                    "type": "string"
                }
            }
        },
        "handler.getAllListsResponse": {
            "type": "object",
            "properties": {
                "data": {
                    "type": "array",
                    "items": {
                        "$ref": "#/definitions/models.TodoList"
                    }
                }
            }
        },
        "handler.signInInput": {
            "type": "object",
            "required": [
                "password",
                "username"
            ],
            "properties": {
                "password": {
                    "description": "Пароль",
                    "type": "string"
                },
                "username": {
                    "description": "Имя пользователя",
                    "type": "string"
                }
            }
        },
        "models.CreateListInput": {
            "type": "object",
            "required": [
                "title"
            ],
            "properties": {
                "description": {
                    "type": "string"
                },
                "title": {
                    "type": "string"
                }
            }
        },
        "models.CreateTodoItemInp": {
            "type": "object",
            "required": [
                "title"
            ],
            "properties": {
                "description": {
                    "type": "string"
                },
                "done": {
                    "type": "boolean"
                },
                "title": {
                    "type": "string"
                }
            }
        },
        "models.ListItem": {
            "type": "object",
            "properties": {
                "id": {
                    "type": "integer"
                },
                "itemId": {
                    "type": "integer"
                },
                "listId": {
                    "type": "integer"
                }
            }
        },
        "models.TodoItem": {
            "type": "object",
            "required": [
                "title"
            ],
            "properties": {
                "description": {
                    "type": "string"
                },
                "done": {
                    "type": "boolean"
                },
                "id": {
                    "type": "integer"
                },
                "title": {
                    "type": "string"
                }
            }
        },
        "models.TodoList": {
            "type": "object",
            "required": [
                "title"
            ],
            "properties": {
                "description": {
                    "type": "string"
                },
                "id": {
                    "type": "integer"
                },
                "title": {
                    "type": "string"
                }
            }
        },
        "models.UpdateItemInput": {
            "type": "object",
            "properties": {
                "description": {
                    "type": "string"
                },
                "done": {
                    "type": "boolean"
                },
                "title": {
                    "type": "string"
                }
            }
        },
        "models.UpdateListInput": {
            "type": "object",
            "properties": {
                "description": {
                    "type": "string"
                },
                "title": {
                    "type": "string"
                }
            }
        },
        "models.User": {
            "type": "object",
            "required": [
                "name",
                "password",
                "username"
            ],
            "properties": {
                "name": {
                    "description": "Тег building Валидирует наличие данного поля в теле запроса",
                    "type": "string"
                },
                "password": {
                    "type": "string"
                },
                "username": {
                    "type": "string"
                }
            }
        }
    },
    "securityDefinitions": {
        "ApiKeyAuth": {
            "type": "apiKey",
            "name": "Authorization",
            "in": "header"
        }
    }
}